sanin/__init__.py
sanin/detectors.py
sanin/injector.py
sanin-1.0.0.dist-info/licenses/LICENSE
sanin-1.0.0.dist-info/METADATA
sanin-1.0.0.dist-info/WHEEL
sanin-1.0.0.dist-info/top_level.txt
sanin-1.0.0.dist-info/RECORD
