Metadata-Version: 2.4
Name: sanin
Version: 1.0.0
Summary: Synthetic anomaly injection for time series with auto baseline estimation.
Author: Mateus Paape
Requires-Python: >=3.8
License-File: LICENSE
Requires-Dist: numpy>=1.22
Requires-Dist: pandas>=1.5
Dynamic: license-file
